new_frontera/__init__.py
new_frontera/_version.py
new_frontera/exceptions.py
new_frontera/contrib/__init__.py
new_frontera/contrib/backends/__init__.py
new_frontera/contrib/backends/partitioners.py
new_frontera/contrib/backends/hbase/__init__.py
new_frontera/contrib/backends/hbase/domaincache.py
new_frontera/contrib/backends/hbase/utils.py
new_frontera/contrib/backends/memory/__init__.py
new_frontera/contrib/backends/redis_backend/__init__.py
new_frontera/contrib/backends/remote/__init__.py
new_frontera/contrib/backends/remote/messagebus.py
new_frontera/contrib/backends/remote/codecs/__init__.py
new_frontera/contrib/backends/remote/codecs/json.py
new_frontera/contrib/backends/remote/codecs/msgpack.py
new_frontera/contrib/backends/sqlalchemy/__init__.py
new_frontera/contrib/backends/sqlalchemy/components.py
new_frontera/contrib/backends/sqlalchemy/models.py
new_frontera/contrib/canonicalsolvers/__init__.py
new_frontera/contrib/canonicalsolvers/basic.py
new_frontera/contrib/canonicalsolvers/common.py
new_frontera/contrib/messagebus/__init__.py
new_frontera/contrib/messagebus/kafkabus.py
new_frontera/contrib/messagebus/kafka/__init__.py
new_frontera/contrib/messagebus/kafka/offsets_fetcher.py
new_frontera/contrib/messagebus/zeromq/__init__.py
new_frontera/contrib/messagebus/zeromq/broker.py
new_frontera/contrib/messagebus/zeromq/socket_config.py
new_frontera/contrib/middlewares/__init__.py
new_frontera/contrib/middlewares/domain.py
new_frontera/contrib/middlewares/fingerprint.py
new_frontera/contrib/requests/__init__.py
new_frontera/contrib/requests/converters.py
new_frontera/contrib/requests/manager.py
new_frontera/contrib/scrapy/__init__.py
new_frontera/contrib/scrapy/converters.py
new_frontera/contrib/scrapy/manager.py
new_frontera/contrib/scrapy/messagebus_stats.py
new_frontera/contrib/scrapy/overusedbuffer.py
new_frontera/contrib/scrapy/settings_adapter.py
new_frontera/contrib/scrapy/middlewares/__init__.py
new_frontera/contrib/scrapy/middlewares/schedulers.py
new_frontera-0.9.0.dist-info/AUTHORS
new_frontera-0.9.0.dist-info/LICENSE
new_frontera-0.9.0.dist-info/METADATA
new_frontera-0.9.0.dist-info/WHEEL
new_frontera-0.9.0.dist-info/top_level.txt
new_frontera-0.9.0.dist-info/RECORD
