Metadata-Version: 2.1
Name: new-frontera
Version: 0.9.0
Summary: A scalable frontier for web crawlers
Home-page: https://github.com/ZeroCool940711/new-frontera
Author: new_frontera developers
Maintainer: Alejandro Gil
License: BSD
Keywords: crawler,frontier,scrapy,web,requests,new_frontera
Classifier: Development Status :: 4 - Beta
Classifier: Environment :: Console
Classifier: Intended Audience :: Developers
Classifier: License :: OSI Approved :: BSD License
Classifier: Operating System :: OS Independent
Classifier: Programming Language :: Python
Classifier: Programming Language :: Python :: 2
Classifier: Programming Language :: Python :: 2.7
Classifier: Programming Language :: Python :: 3
Classifier: Programming Language :: Python :: 3.4
Classifier: Programming Language :: Python :: 3.5
Classifier: Programming Language :: Python :: 3.6
Classifier: Programming Language :: Python :: 3.7
Classifier: Programming Language :: Python :: 3.8
Classifier: Programming Language :: Python :: 3.9
Classifier: Programming Language :: Python :: 3.10
Classifier: Programming Language :: Python :: 3.11
Classifier: Topic :: Internet :: WWW/HTTP
Classifier: Topic :: Software Development :: Libraries :: Application Frameworks
Classifier: Topic :: Software Development :: Libraries :: Python Modules
License-File: LICENSE
License-File: AUTHORS
Requires-Dist: six >=1.8.0
Requires-Dist: w3lib >=1.15.0
Requires-Dist: cityhash >=0.1.7
Provides-Extra: distributed
Requires-Dist: Twisted ; extra == 'distributed'
Provides-Extra: graphs
Requires-Dist: pyparsing ==1.5.7 ; extra == 'graphs'
Requires-Dist: pydot ==1.0.28 ; extra == 'graphs'
Requires-Dist: SQLAlchemy ; extra == 'graphs'
Provides-Extra: hbase
Requires-Dist: happybase >=1.0.0 ; extra == 'hbase'
Requires-Dist: thriftpy2 ; extra == 'hbase'
Provides-Extra: kafka
Requires-Dist: kafka-python >=1.4.0 ; extra == 'kafka'
Provides-Extra: logging
Requires-Dist: colorlog >=2.4.0 ; extra == 'logging'
Requires-Dist: python-json-logger >=0.1.5 ; extra == 'logging'
Provides-Extra: redis
Requires-Dist: redis >=2.10.5 ; extra == 'redis'
Requires-Dist: hiredis >=0.2 ; extra == 'redis'
Provides-Extra: s3
Requires-Dist: boto3 ; extra == 's3'
Provides-Extra: sql
Requires-Dist: SQLAlchemy >=1.0.0 ; extra == 'sql'
Requires-Dist: cachetools ; extra == 'sql'
Provides-Extra: strategies
Requires-Dist: beautifulsoup4 ; extra == 'strategies'
Requires-Dist: publicsuffix ; extra == 'strategies'
Provides-Extra: tldextract
Requires-Dist: tldextract >=1.5.1 ; extra == 'tldextract'
Provides-Extra: zeromq
Requires-Dist: pyzmq ; extra == 'zeromq'
Requires-Dist: msgpack-python >=0.4 ; extra == 'zeromq'
